fkan/__init__.py
fkan/jacobi_polynomials.py
fkan/tensorflow.py
fkan/torch.py
fkan-0.0.2.dist-info/LICENSE
fkan-0.0.2.dist-info/METADATA
fkan-0.0.2.dist-info/WHEEL
fkan-0.0.2.dist-info/top_level.txt
fkan-0.0.2.dist-info/RECORD
