Metadata-Version: 2.1
Name: fkan
Version: 0.0.2
Summary: Fractional Kolmogorov-Arnold Network (fKAN)
Home-page: https://github.com/alirezaafzalaghaei/fkan
Author: Alireza Afzal Aghaei
Author-email: alirezaafzalaghaei@gmail.com
License: BSD
Classifier: Programming Language :: Python :: 3.9
Classifier: Operating System :: OS Independent
Classifier: Topic :: Scientific/Engineering :: Artificial Intelligence
Classifier: Topic :: Scientific/Engineering :: Mathematics
Classifier: License :: OSI Approved :: BSD License
License-File: LICENSE
